{
  "installation_name": "",
  "interactions": [
    {
      "input": {
        "module": "time_input",
        "config": {
          "target_time": "10:00:00"
        }
      },
      "output": {
        "module": "audio_output",
        "config": {
          "file_path": "Sweep.wav",
          "volume": 74
        }
      }
    },
    {
      "input": {
        "module": "frames_input",
        "config": {
          "mode": "trigger",
          "threshold_value": 127,
          "comparison_operator": "="
        }
      },
      "output": {
        "module": "audio_output",
        "config": {
          "file_path": "Arcade.wav",
          "volume": 41
        }
      }
    },
    {
      "input": {
        "module": "time_input",
        "config": {}
      },
      "output": {
        "module": "audio_output",
        "config": {}
      }
    },
    {
      "input": {
        "module": "time_input",
        "config": {
          "target_time": "08:00:00"
        }
      },
      "output": {
        "module": "audio_output",
        "config": {
          "file_path": "Arcade.wav"
        }
      }
    },
    {
      "input": {
        "module": "time_input",
        "config": {
          "target_time": "10:00:00"
        }
      },
      "output": {
        "module": "osc_output",
        "config": {
          "ip_address": "192.168.5.5",
          "port": 8000,
          "address": "/hi"
        }
      }
    }
  ]
}